{
  "project_info": {
    "project_number": "517284951647",
    "project_id": "lab-masters-cf24d",
    "storage_bucket": "lab-masters-cf24d.appspot.com"
  },
  "client": [
    {
      "client_info": {
        "mobilesdk_app_id": "1:517284951647:android:7c6305cb02802e02d04dea",
        "android_client_info": {
          "package_name": "com.example.labmasters"
        }
      },
      "oauth_client": [
        {
          "client_id": "517284951647-c6306rb5ermvj3llunu6qivqc9p0ples.apps.googleusercontent.com",
          "client_type": 1,
          "android_info": {
            "package_name": "com.example.labmasters",
            "certificate_hash": "e2b49815aa30c63aa2818b0a74c20444b13a185e"
          }
        },
        {
          "client_id": "517284951647-ijnm74hq0pbfq0ash9jntmgkhrthupst.apps.googleusercontent.com",
          "client_type": 3
        }
      ],
      "api_key": [
        {
          "current_key": "AIzaSyD_gg9Z8n_evUaqO7PLEi9DKtlBw9CLaGk"
        }
      ],
      "services": {
        "appinvite_service": {
          "other_platform_oauth_client": [
            {
              "client_id": "517284951647-ijnm74hq0pbfq0ash9jntmgkhrthupst.apps.googleusercontent.com",
              "client_type": 3
            }
          ]
        }
      }
    }
  ],
  "configuration_version": "1"
}